nsurl/__init__.py
nsurl/urls.py
nsurl-0.0.1a0.dist-info/METADATA
nsurl-0.0.1a0.dist-info/RECORD
nsurl-0.0.1a0.dist-info/WHEEL
nsurl-0.0.1a0.dist-info/top_level.txt
