Metadata-Version: 1.1
Name: nsurl
Version: 0.0.1a0
Summary: Nationstates API URL generator
Home-page: UNKNOWN
Author: Joshua W
Author-email: DolphDevgithub@gmail.com
License: UNKNOWN
Keywords: nationstates URL Generator
Platform: UNKNOWN
Classifier: License :: OSI Approved :: MIT License
Classifier: Operating System :: OS Independent
Classifier: Topic :: Utilities
Classifier: Programming Language :: Python :: 3.2
Classifier: Programming Language :: Python :: 3.3
Classifier: Programming Language :: Python :: 3.4
Classifier: Programming Language :: Python :: 3.5
Classifier: Programming Language :: Python :: 3.6
